custom_literals/__init__.py
custom_literals-0.1.3.dist-info/LICENSE
custom_literals-0.1.3.dist-info/METADATA
custom_literals-0.1.3.dist-info/WHEEL
custom_literals-0.1.3.dist-info/top_level.txt
custom_literals-0.1.3.dist-info/RECORD
