Metadata-Version: 2.1
Name: custom-literals
Version: 0.1.3
Summary: A module implementing custom literal suffixes using pure Python
Home-page: https://github.com/RocketRace/custom-literals
Author: RocketRace
Author-email: oliviaspalmu@gmail.com
License: UNKNOWN
Project-URL: Bug Tracker, https://github.com/RocketRace/custom-literals/issues
Platform: UNKNOWN
Classifier: Programming Language :: Python :: 3 :: Only
Classifier: Programming Language :: Python :: 3.7
Classifier: Programming Language :: Python :: 3.8
Classifier: Programming Language :: Python :: 3.9
Classifier: Programming Language :: Python :: 3.10
Classifier: License :: OSI Approved :: Mozilla Public License 2.0 (MPL 2.0)
Classifier: Operating System :: OS Independent
Classifier: Environment :: Console
Classifier: Natural Language :: English
Classifier: Topic :: Software Development :: Libraries :: Python Modules
Classifier: Topic :: Utilities
Classifier: Topic :: Internet
Classifier: Typing :: Typed
Classifier: Intended Audience :: Developers
Classifier: Intended Audience :: Information Technology
Requires-Python: >=3.7
License-File: LICENSE
